fraim/__init__.py
fraim/cli.py
fraim/validate_cli.py
fraim/actions/__init__.py
fraim/actions/github.py
fraim/actions/slack.py
fraim/core/contextuals/__init__.py
fraim/core/contextuals/code.py
fraim/core/contextuals/contextual.py
fraim/core/contextuals/status_check.py
fraim/core/display/__init__.py
fraim/core/display/history.py
fraim/core/display/progress.py
fraim/core/display/result.py
fraim/core/history/__init__.py
fraim/core/history/record.py
fraim/core/llms/__init__.py
fraim/core/llms/base.py
fraim/core/llms/litellm.py
fraim/core/llms/tests/__init__.py
fraim/core/llms/tests/test_litellm.py
fraim/core/messages/__init__.py
fraim/core/messages/message.py
fraim/core/parsers/__init__.py
fraim/core/parsers/base.py
fraim/core/parsers/json.py
fraim/core/parsers/pydantic.py
fraim/core/parsers/retry.py
fraim/core/parsers/text.py
fraim/core/parsers/tests/test_pydantic.py
fraim/core/parsers/tests/test_retry.py
fraim/core/prompts/__init__.py
fraim/core/prompts/template.py
fraim/core/prompts/test/test_template.py
fraim/core/steps/base.py
fraim/core/steps/llm.py
fraim/core/tools/__init__.py
fraim/core/tools/base.py
fraim/core/tools/call.py
fraim/core/tools/execute.py
fraim/core/tools/tests/__init__.py
fraim/core/tools/tests/test_execute.py
fraim/core/utils/json.py
fraim/core/utils/retry/__init__.py
fraim/core/utils/retry/http.py
fraim/core/utils/retry/tenacity.py
fraim/core/utils/retry/tests/__init__.py
fraim/core/utils/retry/tests/test_http.py
fraim/core/utils/retry/tests/test_tenacity.py
fraim/core/utils/tests/__init__.py
fraim/core/utils/tests/test_json.py
fraim/core/workflows/__init__.py
fraim/core/workflows/chunk_processing.py
fraim/core/workflows/discovery.py
fraim/core/workflows/filter_processing.py
fraim/core/workflows/format_pr_comment.py
fraim/core/workflows/format_slack_message.py
fraim/core/workflows/llm_processing.py
fraim/core/workflows/sarif.py
fraim/core/workflows/status_checks.py
fraim/core/workflows/workflow.py
fraim/inputs/__init__.py
fraim/inputs/chunks.py
fraim-0.8.0.dist-info/METADATA
fraim-0.8.0.dist-info/WHEEL
fraim-0.8.0.dist-info/entry_points.txt
fraim-0.8.0.dist-info/licenses/LICENSE
fraim-0.8.0.dist-info/RECORD
