Metadata-Version: 2.4
Name: fraim
Version: 0.8.0
Summary: A CLI app that runs AI-powered security workflows
Author-email: Fraim Authors <support@fraim.dev>
License: MIT
License-File: LICENSE
Keywords: ai,automation,cli,directory,langfuse,mcp,packaging,pandas,pydantic,python-dotenv,ratelimit,requests,security,tqdm,tree-sitter,urllib3,uv
Classifier: Development Status :: 3 - Alpha
Classifier: Intended Audience :: Developers
Classifier: License :: OSI Approved :: MIT License
Classifier: Programming Language :: Python :: 3
Classifier: Programming Language :: Python :: 3.12
Classifier: Programming Language :: Python :: 3.13
Classifier: Programming Language :: Python :: 3.14
Requires-Python: >=3.12
Requires-Dist: gitpython<4.0,>=3.1
Requires-Dist: litellm>=1.72.7
Requires-Dist: mcp-server-tree-sitter>=0.5.1
Requires-Dist: openai==1.99.9
Requires-Dist: packaging>=21.0
Requires-Dist: pathspec>=0.12.1
Requires-Dist: pydantic>=2.11.1
Requires-Dist: pygithub>=2.2.0
Requires-Dist: pyyaml>=6.0.2
Requires-Dist: rich>=13.0.0
Requires-Dist: slack-sdk>=3.21.0
Requires-Dist: tenacity==9.1.2
Requires-Dist: types-unidiff>=0.7.0.20240505
Requires-Dist: unidiff<1.0,>=0.7
